Workbook
Name aporte: Planilha1!$D$14
Name patrimonio: Planilha1!$D$17
Name Qtd_anos: Planilha1!$D$15
Name Rendimento_carteira: Planilha1!$D$10
Name taxa_mensal: Planilha1!$D$16

Sheet Planilha1
C8: CONFIGURAÇÕES | G8: Obsevação: Altere somente as céluas/valores que possuem fundo na cor branca.
C9: Salário | D9: 5000
C10: Rendimento da Carteira | D10: 0.0098
C11: Sugestão de Investimento | D11: =D9*30% -> 1500
C13: INVESTIMENTO MENSAL | G13: CENÁRIOS | I13: DIVIDENDOS
C14: Quanto investir por mê? | D14: 900 | G14: Quanto em 2 anos? | H14: =FV($D$16,$B31*12,$D$14*-1) -> 24504.865 | I14: =H14*Rendimento_carteira -> 240.14767
C15: Por quantos anos? | D15: 10 | G15: Quanto em 5 anos? | H15: =FV($D$16,$B32*12,$D$14*-1) -> 75399.223 | I15: =H15*Rendimento_carteira -> 738.91238
C16: Taxa de rendimento mensal? | D16: 0.01079 | G16: Quanto em 10 anos? | H16: =FV($D$16,$B33*12,$D$14*-1) -> 218955.79 | I16: =H16*Rendimento_carteira -> 2145.7668
C17: Patrimônio acumulado? | D17: =FV(taxa_mensal,D15*12,D14*-1) -> 218955.79 | G17: Quanto em 20 anos? | H17: =FV($D$16,$B34*12,$D$14*-1) -> 1012678.6 | I17: =H17*Rendimento_carteira -> 9924.2499
C18: Divendendos mensais? | D18: =patrimonio*Rendimento_carteira -> 2145.7668 | G18: Quanto em 30 anos? | H18: =FV($D$16,$B35*12,$D$14*-1) -> 3889952.7 | I18: =H18*Rendimento_carteira -> 38121.536
C20: PERFIL | D20: Conservador
C21: VALOR A SER INVESTIDO POR MÊS | D21: =aporte -> 900
C23: TIPO DE FII | D23: PERCENTUAL SUGERIDO | E23: VALORES
C24: PAPEL | D24: =VLOOKUP($D$20&"-"&C24,'P-Apoio'!A2:D20,4,FALSE) -> 0.3 | E24: =D24*$D$21 -> 270
C25: TIJOLO | D25: =VLOOKUP($D$20&"-"&C25,'P-Apoio'!A3:D21,4,FALSE) -> 0.5 | E25: =D25*$D$21 -> 450
C26: HÍBRIDOS | D26: =VLOOKUP($D$20&"-"&C26,'P-Apoio'!A4:D22,4,FALSE) -> 0.1 | E26: =D26*$D$21 -> 90
C27: FOFs | D27: =VLOOKUP($D$20&"-"&C27,'P-Apoio'!A5:D23,4,FALSE) -> 0.1 | E27: =D27*$D$21 -> 90
C28: DESENVOLVIMENTO | D28: =VLOOKUP($D$20&"-"&C28,'P-Apoio'!A6:D24,4,FALSE) -> 0 | E28: =D28*$D$21 -> 0
C29: HOTELARIAS | D29: =VLOOKUP($D$20&"-"&C29,'P-Apoio'!A7:D25,4,FALSE) -> 0 | E29: =D29*$D$21 -> 0
E30: =SUM(E24:E29) -> 900
B31: 2
B32: 5
B33: 10
B34: 20
B35: 30

Sheet P-Apoio
A2: Chave | B2: PERFIL | C2: TIPO DE FII | D2: %
A3: =B3&"-"&C3 -> Conservador-PAPEL | B3: Conservador | C3: PAPEL | D3: 0.3
A4: =B4&"-"&C4 -> Conservador-TIJOLO | B4: Conservador | C4: TIJOLO | D4: 0.5
A5: =B5&"-"&C5 -> Conservador-HÍBRIDOS | B5: Conservador | C5: HÍBRIDOS | D5: 0.1
A6: =B6&"-"&C6 -> Conservador-FOFs | B6: Conservador | C6: FOFs | D6: 0.1
A7: =B7&"-"&C7 -> Conservador-DESENVOLVIMENTO | B7: Conservador | C7: DESENVOLVIMENTO | D7: 0
A8: =B8&"-"&C8 -> Conservador-HOTELARIAS | B8: Conservador | C8: HOTELARIAS | D8: 0
A9: =B9&"-"&C9 -> Moderado-PAPEL | B9: Moderado | C9: PAPEL | D9: 0.32
A10: =B10&"-"&C10 -> Moderado-TIJOLO | B10: Moderado | C10: TIJOLO | D10: 0.4
A11: =B11&"-"&C11 -> Moderado-HÍBRIDOS | B11: Moderado | C11: HÍBRIDOS | D11: 0.08
A12: =B12&"-"&C12 -> Moderado-FOFs | B12: Moderado | C12: FOFs | D12: 0.1
A13: =B13&"-"&C13 -> Moderado-DESENVOLVIMENTO | B13: Moderado | C13: DESENVOLVIMENTO | D13: 0.05
A14: =B14&"-"&C14 -> Moderado-HOTELARIAS | B14: Moderado | C14: HOTELARIAS | D14: 0.05
... A20: =B20&"-"&C20 -> Agressivo-HOTELARIAS | B20: Agressivo | C20: HOTELARIAS | D20: 0.1
